dockler/__init__.py
dockler/py.typed
dockler-0.0.1.dist-info/METADATA
dockler-0.0.1.dist-info/WHEEL
dockler-0.0.1.dist-info/licenses/LICENSE
dockler-0.0.1.dist-info/RECORD
