Metadata-Version: 2.4
Name: dockler
Version: 0.0.1
Summary: Docker launcher / management
Project-URL: Documentation, https://phil65.github.io/dockler/
Project-URL: Source, https://github.com/phil65/dockler
Project-URL: Issues, https://github.com/phil65/dockler/issues
Project-URL: Discussions, https://github.com/phil65/dockler/discussions
Project-URL: Code coverage, https://app.codecov.io/gh/phil65/dockler
Author-email: Philipp Temminghoff <philipptemminghoff@googlemail.com>
License: MIT License
License-File: LICENSE
Classifier: Development Status :: 4 - Beta
Classifier: Intended Audience :: Developers
Classifier: Operating System :: OS Independent
Classifier: Programming Language :: Python :: 3
Classifier: Programming Language :: Python :: 3 :: Only
Classifier: Programming Language :: Python :: 3.12
Classifier: Programming Language :: Python :: 3.13
Classifier: Programming Language :: Python :: 3.14
Classifier: Topic :: Documentation
Classifier: Topic :: Software Development
Classifier: Topic :: Utilities
Classifier: Typing :: Typed
Requires-Python: >=3.12
